pyteamcity/__init__.py
pyteamcity/legacy/__init__.py
pyteamcity/legacy/legacy.py
pyteamcity/legacy/test_legacy.py
pyteamcity-0.1.1.dist-info/DESCRIPTION.rst
pyteamcity-0.1.1.dist-info/METADATA
pyteamcity-0.1.1.dist-info/metadata.json
pyteamcity-0.1.1.dist-info/RECORD
pyteamcity-0.1.1.dist-info/top_level.txt
pyteamcity-0.1.1.dist-info/WHEEL
