Metadata-Version: 2.0
Name: pyteamcity
Version: 0.1.1
Summary: Use the TeamCity REST API from Python
Home-page: https://github.com/SurveyMonkey/pyteamcity
Author: Marc Abramowitz
Author-email: marc@marc-abramowitz.com
License: MIT
Platform: UNKNOWN
Classifier: Programming Language :: Python :: 2
Classifier: Programming Language :: Python :: 2.6
Classifier: Programming Language :: Python :: 2.7
Classifier: Programming Language :: Python :: 3
Classifier: Programming Language :: Python :: 3.2
Classifier: Programming Language :: Python :: 3.3
Classifier: Programming Language :: Python :: 3.4
Classifier: Programming Language :: Python :: 3.5
Classifier: Natural Language :: English
Classifier: Intended Audience :: Developers
Requires-Dist: beautifulsoup4
Requires-Dist: python-dateutil
Requires-Dist: pytz
Requires-Dist: requests
Requires-Dist: six
